<?xml version="1.0" encoding="utf-8" ?><dwsync><file name=".DS_Store" server="octo.ubermind.com//var/www/html/clients/invista/" local="3466541791" remote="319783739110406879" Dst="-1" /><file name="invista-logo.gif" server="octo.ubermind.com//var/www/html/clients/invista/" local="3464705982" remote="319783739108751690" Dst="-1" /><file name="tab-bg.gif" server="octo.ubermind.com//var/www/html/clients/invista/" local="3464717402" remote="319783739108751690" Dst="-1" /><file name="updown2.gif" server="octo.ubermind.com//var/www/html/clients/invista/" local="3464804809" remote="319783739108751690" Dst="-1" /><file name="cnav-bg.gif" server="octo.ubermind.com//var/www/html/clients/invista/" local="3464891350" remote="319783739108766711" Dst="-1" /><file name="tab-bg-hover.gif" server="octo.ubermind.com//var/www/html/clients/invista/" local="3464892871" remote="319783739108766711" Dst="-1" /><file name="togglebar-bg.gif" server="octo.ubermind.com//var/www/html/clients/invista/" local="3465253451" remote="319783739109166834" Dst="-1" /><file name="togglebar-gif.gif" server="octo.ubermind.com//var/www/html/clients/invista/" local="3465253435" remote="319783739109282874" Dst="-1" /><file name="favicon.ico" server="octo.ubermind.com//var/www/html/clients/invista/" local="3465854639" remote="319783739109720203" Dst="-1" /><file name="move.gif" server="octo.ubermind.com//var/www/html/clients/invista/" local="3465932923" remote="319783739109798430" Dst="-1" /><file name="items.png" server="octo.ubermind.com//var/www/html/clients/invista/" local="3465934479" remote="319783739109802597" Dst="-1" /><file name="delivery.png" server="octo.ubermind.com//var/www/html/clients/invista/" local="3465934479" remote="319783739109802597" Dst="-1" /><file name="shipment.png" server="octo.ubermind.com//var/www/html/clients/invista/" local="3465934413" remote="319783739109802597" Dst="-1" /><file name="confirmed.png" server="octo.ubermind.com//var/www/html/clients/invista/" local="3466455735" remote="319783739110325779" Dst="-1" /><file name="created.png" server="octo.ubermind.com//var/www/html/clients/invista/" local="3466025105" remote="319783739109892333" Dst="-1" /><file name="picked.png" server="octo.ubermind.com//var/www/html/clients/invista/" local="3466025116" remote="319783739109892333" Dst="-1" /><file name="process.png" server="octo.ubermind.com//var/www/html/clients/invista/" local="3466025124" remote="319783739109892333" Dst="-1" /><file name="shipped.png" server="octo.ubermind.com//var/www/html/clients/invista/" local="3466025132" remote="319783739109892333" Dst="-1" /><file name="intransit.png" server="octo.ubermind.com//var/www/html/clients/invista/" local="3466025151" remote="319783739109892333" Dst="-1" /><file name="delivered.png" server="octo.ubermind.com//var/www/html/clients/invista/" local="3466025164" remote="319783739109892333" Dst="-1" /><file name="changeorder.png" server="octo.ubermind.com//var/www/html/clients/invista/" local="3466539797" remote="319783739110406879" Dst="-1" /><file name="customerlist.png" server="octo.ubermind.com//var/www/html/clients/invista/" local="3466539852" remote="319783739110406879" Dst="-1" /><file name="delivery.gif" server="octo.ubermind.com//var/www/html/clients/invista/" local="3465933322" remote="319783739110406879" Dst="-1" /><file name="displaycustomer.png" server="octo.ubermind.com//var/www/html/clients/invista/" local="3466539782" remote="319783739110406879" Dst="-1" /><file name="displayorder.png" server="octo.ubermind.com//var/www/html/clients/invista/" local="3466539760" remote="319783739110406879" Dst="-1" /><file name="emailcustomer.png" server="octo.ubermind.com//var/www/html/clients/invista/" local="3466539683" remote="319783739110406879" Dst="-1" /><file name="emailteam.png" server="octo.ubermind.com//var/www/html/clients/invista/" local="3466539665" remote="319783739110406879" Dst="-1" /><file name="items.gif" server="octo.ubermind.com//var/www/html/clients/invista/" local="3465933322" remote="319783739110406879" Dst="-1" /><file name="materialavailability.png" server="octo.ubermind.com//var/www/html/clients/invista/" local="3466539821" remote="319783739110406879" Dst="-1" /><file name="shipment.gif" server="octo.ubermind.com//var/www/html/clients/invista/" local="3465933322" remote="319783739110406879" Dst="-1" /><file name="viewinventory.png" server="octo.ubermind.com//var/www/html/clients/invista/" local="3466539834" remote="319783739110406879" Dst="-1" /><file name="ordertrackerbg.png" server="octo.ubermind.com//var/www/html/clients/invista/" local="3466545001" remote="319783739110411256" Dst="-1" /><file name="selectedstategradient.png" server="octo.ubermind.com//var/www/html/clients/invista/" local="3466694438" remote="319783739110559704" Dst="-1" /><file name="OrderTracker-BKGRND.png" server="octo.ubermind.com//var/www/html/clients/invista/" local="3467138626" remote="319783739111004476" Dst="-1" /><file name="legendchart.jpg" server="octo.ubermind.com//var/www/html/clients/invista/" local="3467240731" remote="319783739111105702" Dst="-1" /><file name="long-legend-pie.jpg" server="octo.ubermind.com//var/www/html/clients/invista/" local="3467292365" remote="319783739111157598" Dst="-1" /></dwsync>